LICENSE
README.rst
setup.py
sh_nic_api/__init__.py
sh_nic_api/exceptions.py
sh_nic_api/models.py
sh_nic_api.egg-info/PKG-INFO
sh_nic_api.egg-info/SOURCES.txt
sh_nic_api.egg-info/dependency_links.txt
sh_nic_api.egg-info/requires.txt
sh_nic_api.egg-info/top_level.txt