Metadata-Version: 2.1
Name: sh-nic-api
Version: 1.0.3
Summary: NIC.RU API Python library
Home-page: https://github.com/andr1an/nic-api
Author: Sergey Andrianov; Alexey Matveev
License: GPLv3
Project-URL: Bug Reports, https://github.com/shizacat/nic-api/issues
Project-URL: Source, https://github.com/shizacat/nic-api
Classifier: Development Status :: 3 - Alpha
Classifier: Topic :: Internet :: Name Service (DNS)
Classifier: License :: OSI Approved :: GNU General Public License v3 (GPLv3)
Classifier: Programming Language :: Python
Classifier: Programming Language :: Python :: 3
Classifier: Programming Language :: Python :: 3.6
Classifier: Programming Language :: Python :: 3.7
Classifier: Programming Language :: Python :: 3.8
Classifier: Programming Language :: Python :: 3.9
Requires-Python: >=3.6, <4.0
License-File: LICENSE
